env_show/__init__.py
env_show/router.py
env_show-0.4.0.dist-info/METADATA
env_show-0.4.0.dist-info/WHEEL
env_show-0.4.0.dist-info/top_level.txt
env_show-0.4.0.dist-info/RECORD
