Metadata-Version: 2.1
Name: env-show
Version: 0.4.0
Summary: FastAPI plugin to expose .env values via an endpoint
Home-page: UNKNOWN
Author: test
License: UNKNOWN
Platform: UNKNOWN
Classifier: Programming Language :: Python :: 3
Classifier: Framework :: FastAPI
Classifier: License :: OSI Approved :: MIT License
Requires-Dist: fastapi
Requires-Dist: python-dotenv
